{
    "keep": {
        "days": true,
        "amount": 14
    },
    "auditLog": "D:\\Respositories\\SEP490_G40_SP26\\backend\\src\\logs\\.f35182cbf82fc176271bae6a5a1329550be868e0-audit.json",
    "files": [
        {
            "date": 1771925598997,
            "name": "D:\\Respositories\\SEP490_G40_SP26\\backend\\src\\logs\\application-2026-02-24.log",
            "hash": "0b36deed88df100fc1ac216f62a0aa7aa73846a6b34f566292df7c65c5abe195"
        },
        {
            "date": 1772004936631,
            "name": "D:\\Respositories\\SEP490_G40_SP26\\backend\\src\\logs\\application-2026-02-25.log",
            "hash": "a5ca0aad162f565a3d8e03a6fa17da3e887fd29803ff8e621cffa6a3808d1bb8"
        },
        {
            "date": 1772097982032,
            "name": "D:\\Respositories\\SEP490_G40_SP26\\backend\\src\\logs\\application-2026-02-26.log",
            "hash": "124981a054d26b8a3dc156c2148f3192810fe5d31bf821144459517408e9fd4f"
        },
        {
            "date": 1772627969597,
            "name": "D:\\Respositories\\SEP490_G40_SP26\\backend\\src\\logs\\application-2026-03-04.log",
            "hash": "043d0e05d985bf444782b00aea0d7a4fdcf83072609e2210ba9260fcba107d1c"
        },
        {
            "date": 1772700032610,
            "name": "D:\\Respositories\\SEP490_G40_SP26\\backend\\src\\logs\\application-2026-03-05.log",
            "hash": "1a0790cd98229d7785fb1c0839f7654808b9284234f8ba4a119497aa0342defb"
        },
        {
            "date": 1772886999725,
            "name": "D:\\Respositories\\SEP490_G40_SP26\\backend\\src\\logs\\application-2026-03-07.log",
            "hash": "a3caf2bdcc18edbdfdc41af42bf713c80d6c50de9635a8c2885d3a936f17e1fb"
        },
        {
            "date": 1773017739310,
            "name": "D:\\Respositories\\SEP490_G40_SP26\\backend\\src\\logs\\application-2026-03-09.log",
            "hash": "b8043b44ae2f287310ff8eb85c7eacd0e063b993a7a1b608f6c04b3e2f2fda95"
        }
    ],
    "hashType": "sha256"
}